README.md
setup.cfg
setup.py
src/montapy/core/__init__.py
src/montapy/core/mixins/__init__.py
src/montapy/core/mixins/logger.py
src/montapy_core.egg-info/PKG-INFO
src/montapy_core.egg-info/SOURCES.txt
src/montapy_core.egg-info/dependency_links.txt
src/montapy_core.egg-info/requires.txt
src/montapy_core.egg-info/top_level.txt