Metadata-Version: 2.1
Name: montapy-core
Version: 0.3.1
Summary: Shared core for all montapy packages
Home-page: https://github.com/montapy/core
Author: Sergey Volkov
Author-email: volkov.sergey.e@gmail.com
License: MIT
Project-URL: CI: Travis, https://travis-ci.com/montapy/core
Project-URL: GitHub: issues, https://github.com/montapy/core/issues
Project-URL: GitHub: repo, https://github.com/montapy/core
Platform: UNKNOWN
Classifier: Development Status :: 2 - Pre-Alpha
Classifier: Intended Audience :: Developers
Classifier: Framework :: AsyncIO
Classifier: License :: OSI Approved :: MIT License
Classifier: Programming Language :: Python
Classifier: Programming Language :: Python :: 3
Classifier: Programming Language :: Python :: 3.7
Classifier: Programming Language :: Python :: 3.8
Classifier: Programming Language :: Python :: 3.9
Classifier: Topic :: Software Development
Classifier: Topic :: Utilities
Provides-Extra: test
Provides-Extra: dev
